Workbook
Name 姓名列表: 班级名单!$B$2:$B$44

Sheet 使用说明
A1: 班级家委会财务记账簿
A3: 使用步骤 | B3: 1. 每发生一笔收支，在“收支明细”新增一行。
A4: 填写规则 | B4: 2. 收入填写“收入金额”，支出填写“支出金额”，另一栏留空。
A5: 自动汇总 | B5: 3. “个人汇总”会按姓名自动统计收入、支出、余额和笔数。
A6: 凭证管理 | B6: 4. 建议填写凭证编号，并保留收据、转账截图或发票。
A7: 名单范围 | B7: 当前依据截图中可见的第1–43名建立；其余名单可继续添加。
A8: 余额口径 | B8: 余额 = 累计收入 - 累计支出。

Sheet 班级名单
A1: 序号 | B1: 姓名
A2: 1 | B2: 包亦宸
A3: 2 | B3: 陈又可
A4: 3 | B4: 陈洁言
A5: 4 | B5: 陈曦
A6: 5 | B6: 陈骐跃
A7: 6 | B7: 程翔嘉
A8: 7 | B8: 丁彦清
A9: 8 | B9: 丁思佳
A10: 9 | B10: 傅沛霖
A11: 10 | B11: 方允
A12: 11 | B12: 范重南
A13: 12 | B13: 黄萌琦
... A44: 43 | B44: 赵修毅

Sheet 收支明细
A1: 日期 | B1: 姓名 | C1: 事项/用途 | D1: 收入金额（元） | E1: 支出金额（元） | F1: 支付方式 | G1: 经办人 | H1: 凭证编号 | I1: 备注

Sheet 个人汇总
A1: 序号 | B1: 姓名 | C1: 累计收入（元） | D1: 累计支出（元） | E1: 当前余额（元） | F1: 收支笔数 | G1: 最近记账日期
A2: 1 | B2: 包亦宸 | C2: =SUMIFS(收支明细!D:D,收支明细!B:B,B2) -> 0 | D2: =SUMIFS(收支明细!E:E,收支明细!B:B,B2) -> 0 | E2: =C2-D2 -> 0 | F2: =COUNTIF(收支明细!B:B,B2) -> 0 | G2: =IFERROR(_xlfn.AGGREGATE(14,6,收支明细!A$2:A$501/(收支明细!B$2:B$501=B2),1),"")
A3: 2 | B3: 陈又可 | C3: =SUMIFS(收支明细!D:D,收支明细!B:B,B3) -> 0 | D3: =SUMIFS(收支明细!E:E,收支明细!B:B,B3) -> 0 | E3: =C3-D3 -> 0 | F3: =COUNTIF(收支明细!B:B,B3) -> 0 | G3: =IFERROR(_xlfn.AGGREGATE(14,6,收支明细!A$2:A$501/(收支明细!B$2:B$501=B3),1),"")
A4: 3 | B4: 陈洁言 | C4: =SUMIFS(收支明细!D:D,收支明细!B:B,B4) -> 0 | D4: =SUMIFS(收支明细!E:E,收支明细!B:B,B4) -> 0 | E4: =C4-D4 -> 0 | F4: =COUNTIF(收支明细!B:B,B4) -> 0 | G4: =IFERROR(_xlfn.AGGREGATE(14,6,收支明细!A$2:A$501/(收支明细!B$2:B$501=B4),1),"")
A5: 4 | B5: 陈曦 | C5: =SUMIFS(收支明细!D:D,收支明细!B:B,B5) -> 0 | D5: =SUMIFS(收支明细!E:E,收支明细!B:B,B5) -> 0 | E5: =C5-D5 -> 0 | F5: =COUNTIF(收支明细!B:B,B5) -> 0 | G5: =IFERROR(_xlfn.AGGREGATE(14,6,收支明细!A$2:A$501/(收支明细!B$2:B$501=B5),1),"")
A6: 5 | B6: 陈骐跃 | C6: =SUMIFS(收支明细!D:D,收支明细!B:B,B6) -> 0 | D6: =SUMIFS(收支明细!E:E,收支明细!B:B,B6) -> 0 | E6: =C6-D6 -> 0 | F6: =COUNTIF(收支明细!B:B,B6) -> 0 | G6: =IFERROR(_xlfn.AGGREGATE(14,6,收支明细!A$2:A$501/(收支明细!B$2:B$501=B6),1),"")
A7: 6 | B7: 程翔嘉 | C7: =SUMIFS(收支明细!D:D,收支明细!B:B,B7) -> 0 | D7: =SUMIFS(收支明细!E:E,收支明细!B:B,B7) -> 0 | E7: =C7-D7 -> 0 | F7: =COUNTIF(收支明细!B:B,B7) -> 0 | G7: =IFERROR(_xlfn.AGGREGATE(14,6,收支明细!A$2:A$501/(收支明细!B$2:B$501=B7),1),"")
A8: 7 | B8: 丁彦清 | C8: =SUMIFS(收支明细!D:D,收支明细!B:B,B8) -> 0 | D8: =SUMIFS(收支明细!E:E,收支明细!B:B,B8) -> 0 | E8: =C8-D8 -> 0 | F8: =COUNTIF(收支明细!B:B,B8) -> 0 | G8: =IFERROR(_xlfn.AGGREGATE(14,6,收支明细!A$2:A$501/(收支明细!B$2:B$501=B8),1),"")
A9: 8 | B9: 丁思佳 | C9: =SUMIFS(收支明细!D:D,收支明细!B:B,B9) -> 0 | D9: =SUMIFS(收支明细!E:E,收支明细!B:B,B9) -> 0 | E9: =C9-D9 -> 0 | F9: =COUNTIF(收支明细!B:B,B9) -> 0 | G9: =IFERROR(_xlfn.AGGREGATE(14,6,收支明细!A$2:A$501/(收支明细!B$2:B$501=B9),1),"")
A10: 9 | B10: 傅沛霖 | C10: =SUMIFS(收支明细!D:D,收支明细!B:B,B10) -> 0 | D10: =SUMIFS(收支明细!E:E,收支明细!B:B,B10) -> 0 | E10: =C10-D10 -> 0 | F10: =COUNTIF(收支明细!B:B,B10) -> 0 | G10: =IFERROR(_xlfn.AGGREGATE(14,6,收支明细!A$2:A$501/(收支明细!B$2:B$501=B10),1),"")
A11: 10 | B11: 方允 | C11: =SUMIFS(收支明细!D:D,收支明细!B:B,B11) -> 0 | D11: =SUMIFS(收支明细!E:E,收支明细!B:B,B11) -> 0 | E11: =C11-D11 -> 0 | F11: =COUNTIF(收支明细!B:B,B11) -> 0 | G11: =IFERROR(_xlfn.AGGREGATE(14,6,收支明细!A$2:A$501/(收支明细!B$2:B$501=B11),1),"")
A12: 11 | B12: 范重南 | C12: =SUMIFS(收支明细!D:D,收支明细!B:B,B12) -> 0 | D12: =SUMIFS(收支明细!E:E,收支明细!B:B,B12) -> 0 | E12: =C12-D12 -> 0 | F12: =COUNTIF(收支明细!B:B,B12) -> 0 | G12: =IFERROR(_xlfn.AGGREGATE(14,6,收支明细!A$2:A$501/(收支明细!B$2:B$501=B12),1),"")
A13: 12 | B13: 黄萌琦 | C13: =SUMIFS(收支明细!D:D,收支明细!B:B,B13) -> 0 | D13: =SUMIFS(收支明细!E:E,收支明细!B:B,B13) -> 0 | E13: =C13-D13 -> 0 | F13: =COUNTIF(收支明细!B:B,B13) -> 0 | G13: =IFERROR(_xlfn.AGGREGATE(14,6,收支明细!A$2:A$501/(收支明细!B$2:B$501=B13),1),"")
... A44: 43 | B44: 赵修毅 | C44: =SUMIFS(收支明细!D:D,收支明细!B:B,B44) -> 0 | D44: =SUMIFS(收支明细!E:E,收支明细!B:B,B44) -> 0 | E44: =C44-D44 -> 0 | F44: =COUNTIF(收支明细!B:B,B44) -> 0 | G44: =IFERROR(_xlfn.AGGREGATE(14,6,收支明细!A$2:A$501/(收支明细!B$2:B$501=B44),1),"")
A45: 合计 | C45: =SUM(C2:C44) -> 0 | D45: =SUM(D2:D44) -> 0 | E45: =C45-D45 -> 0 | F45: =SUM(F2:F44) -> 0
